python_crypto/__init__.py
python_crypto/awscrypto.py
python_crypto/cryptocli.py
python_crypto/customcrypto.py
python_crypto/utils.py
samsteady_python_crypto-1.0.19.dist-info/METADATA
samsteady_python_crypto-1.0.19.dist-info/WHEEL
samsteady_python_crypto-1.0.19.dist-info/top_level.txt
samsteady_python_crypto-1.0.19.dist-info/RECORD
