Metadata-Version: 2.1
Name: samsteady-python-crypto
Version: 1.0.19
Summary: Crypto tools for python
License: MIT
Classifier: Development Status :: 4 - Beta
Classifier: Environment :: Web Environment
Classifier: Intended Audience :: Developers
Classifier: License :: OSI Approved :: MIT License
Classifier: Operating System :: OS Independent
Classifier: Programming Language :: Python :: 3 :: Only
Classifier: Programming Language :: Python :: 3.7
Classifier: Programming Language :: Python :: Implementation :: CPython
Classifier: Topic :: Software Development :: Libraries :: Application Frameworks
Classifier: Topic :: Software Development :: Libraries :: Python Modules
Requires-Python: >=3.6
Requires-Dist: aes-everywhere (==1.2.10)
Requires-Dist: cryptography (>=3.1.1)
Requires-Dist: boto3 (==1.15.10)
Requires-Dist: aws-encryption-sdk (>=3.0.0)
Requires-Dist: get-docker-secret (==1.0.1)
